pycopanlpjml/__init__.py
pycopanlpjml/_version.py
pycopanlpjml/cell.py
pycopanlpjml/component.py
pycopanlpjml/config.yaml
pycopanlpjml/world.py
pycopanlpjml-1.1.9.dist-info/METADATA
pycopanlpjml-1.1.9.dist-info/WHEEL
pycopanlpjml-1.1.9.dist-info/licenses/LICENSE.md
pycopanlpjml-1.1.9.dist-info/RECORD
