Metadata-Version: 2.4
Name: pycopanlpjml
Version: 1.1.9
Summary: copan:LPJmL, an advanced World-Earth modeling framework extending copan:CORE, integrating LPJmL as the Earth system interface for comprehensive social-ecological simulations.
Project-URL: Homepage, https://github.com/pik-copan/pycopanlpjml
Project-URL: Issues, https://github.com/pik-copan/pycopanlpjml/issues
Project-URL: Documentation, https://pycopanlpjml.readthedocs.io/en/latest/
Project-URL: Repository, https://github.com/pik-copan/pycopanlpjml
Author-email: Jannes Breier <jannes.breier@pik-potsdam.de>
License: ## GNU Affero General Public License (AGPL)
License-File: LICENSE.md
Keywords: ABM,DGVM,LPJmL,copan:CORE
Classifier: Development Status :: 4 - Beta
Classifier: Intended Audience :: Developers
Classifier: Intended Audience :: Science/Research
Classifier: Operating System :: OS Independent
Classifier: Programming Language :: Python
Classifier: Programming Language :: Python :: 3.9
Classifier: Programming Language :: Python :: 3.10
Classifier: Programming Language :: Python :: 3.11
Classifier: Programming Language :: Python :: 3.12
Classifier: Topic :: Scientific/Engineering
Classifier: Topic :: Software Development :: Libraries
Requires-Python: >=3.9
Requires-Dist: netcdf4>=1.5.8
Requires-Dist: networkx>=2.6.3
Requires-Dist: numpy>=1.20.3
Requires-Dist: pycopancore>=0.8.5
Requires-Dist: pycoupler>=1.5.16
Requires-Dist: xarray>=0.21.1
Provides-Extra: dev
Requires-Dist: black; extra == 'dev'
Requires-Dist: flake8; extra == 'dev'
Requires-Dist: pytest; extra == 'dev'
Requires-Dist: pytest-cov; extra == 'dev'
Provides-Extra: doc
Requires-Dist: ablog>=0.10; extra == 'doc'
Requires-Dist: docutils>=0.18; extra == 'doc'
Requires-Dist: myst-parser>=1.0; extra == 'doc'
Requires-Dist: numpydoc>=1.1; extra == 'doc'
Requires-Dist: pydata-sphinx-theme>=0.16.0; extra == 'doc'
Requires-Dist: sphinx-design>=0.4; extra == 'doc'
Requires-Dist: sphinx>=6; extra == 'doc'
Requires-Dist: sphinxcontrib-mermaid>=0.7; extra == 'doc'
